lexicon_overlap_score/__init__.py
lexicon_overlap_score/los.py
lexicon_overlap_score-0.0.1.dist-info/LICENSE
lexicon_overlap_score-0.0.1.dist-info/METADATA
lexicon_overlap_score-0.0.1.dist-info/WHEEL
lexicon_overlap_score-0.0.1.dist-info/top_level.txt
lexicon_overlap_score-0.0.1.dist-info/RECORD
