Metadata-Version: 2.1
Name: lexicon-overlap-score
Version: 0.0.1
Summary: Functions for calculation of the lexicon overlap score
Home-page: https://gitlab.rrz.uni-hamburg.de/bay1620/lexicon_overlap_score
Author: Felix Welter
Author-email: felixwelter@gmail.com
License: UNKNOWN
Platform: UNKNOWN
Classifier: Programming Language :: Python :: 3
Classifier: License :: OSI Approved :: MIT License
Classifier: Operating System :: OS Independent
Requires-Python: >=3.6
Requires-Dist: numpy (>=1)
Requires-Dist: pandas
